distutils/__init__.py
distutils/_msvccompiler.py
distutils/archive_util.py
distutils/bcppcompiler.py
distutils/ccompiler.py
distutils/cmd.py
distutils/config.py
distutils/core.py
distutils/cygwinccompiler.py
distutils/debug.py
distutils/dep_util.py
distutils/dir_util.py
distutils/dist.py
distutils/errors.py
distutils/extension.py
distutils/fancy_getopt.py
distutils/file_util.py
distutils/filelist.py
distutils/log.py
distutils/msvc9compiler.py
distutils/msvccompiler.py
distutils/spawn.py
distutils/sysconfig.py
distutils/text_file.py
distutils/unixccompiler.py
distutils/util.py
distutils/version.py
distutils/versionpredicate.py
distutils/command/__init__.py
distutils/command/bdist.py
distutils/command/bdist_dumb.py
distutils/command/bdist_msi.py
distutils/command/bdist_rpm.py
distutils/command/build.py
distutils/command/build_clib.py
distutils/command/build_ext.py
distutils/command/build_py.py
distutils/command/build_scripts.py
distutils/command/check.py
distutils/command/clean.py
distutils/command/config.py
distutils/command/install.py
distutils/command/install_data.py
distutils/command/install_egg_info.py
distutils/command/install_headers.py
distutils/command/install_lib.py
distutils/command/install_scripts.py
distutils/command/register.py
distutils/command/sdist.py
distutils/command/upload.py
distutils/tests/__init__.py
distutils/tests/support.py
distutils/tests/test_archive_util.py
distutils/tests/test_bdist.py
distutils/tests/test_bdist_dumb.py
distutils/tests/test_bdist_msi.py
distutils/tests/test_bdist_rpm.py
distutils/tests/test_build.py
distutils/tests/test_build_clib.py
distutils/tests/test_build_ext.py
distutils/tests/test_build_py.py
distutils/tests/test_build_scripts.py
distutils/tests/test_check.py
distutils/tests/test_clean.py
distutils/tests/test_cmd.py
distutils/tests/test_config.py
distutils/tests/test_config_cmd.py
distutils/tests/test_core.py
distutils/tests/test_cygwinccompiler.py
distutils/tests/test_dep_util.py
distutils/tests/test_dir_util.py
standard_distutils-3.10.14.dist-info/LICENSE
standard_distutils-3.10.14.dist-info/METADATA
standard_distutils-3.10.14.dist-info/WHEEL
standard_distutils-3.10.14.dist-info/top_level.txt
standard_distutils-3.10.14.dist-info/RECORD
